<Active>

	<Name>Greater Fire Attunement</Name>
	<Description>Enchant your weaponry with intense fire.</Description>

	<Cooldown>22</Cooldown>
	<Range>1</Range>

	<Icon>
		<Name>Icons/BurningBlades</Name>
		<Colour><RGB>255,185,50</RGB></Colour>
	</Icon>

	<HitType>
		<Self></Self>
	</HitType>

	<Effect>
		<Status>
            <Duration>10</Duration>
            <Events>
                <Constant>
                    <Attack>20 + level * 2</Attack>
                </Constant>
            </Events>
		</Status>
	</Effect>

</Active>